<?xml version="1.0" encoding="UTF-8"?>
<tv generator-info-name="WebGrab+Plus/w MDB &amp; REX Postprocess -- version  V3.3.0.0 -- Jan van Straaten" generator-info-url="http://www.webgrabplus.com">
  <channel id="RECORD TV HD">
    <display-name lang="pt">RECORD TV HD</display-name>
    <icon src="https://www.meo.pt/PublishingImages/canais/tv-record.png" />
    <url>http://www.meo.pt</url>
  </channel>
  <channel id="ELEVEN 1">
    <display-name lang="pt">ELEVEN 1</display-name>
    <url>http://www.meo.pt</url>
  </channel>
  <channel id="ELEVEN 2">
    <display-name lang="pt">ELEVEN 2</display-name>
    <url>http://www.meo.pt</url>
  </channel>
  <channel id="ELEVEN 3">
    <display-name lang="pt">ELEVEN 3</display-name>
    <url>http://www.meo.pt</url>
  </channel>
  <channel id="ELEVEN 4">
    <display-name lang="pt">ELEVEN 4</display-name>
    <url>http://www.meo.pt</url>
  </channel>
  <channel id="ELEVEN 5">
    <display-name lang="pt">ELEVEN 5</display-name>
    <url>http://www.meo.pt</url>
  </channel>
  <channel id="ELEVEN 6">
    <display-name lang="pt">ELEVEN 6</display-name>
    <url>http://www.meo.pt</url>
  </channel>
  <channel id="SPORT.TV1">
    <display-name lang="pt">SPORT.TV1</display-name>
    <url>http://www.meo.pt</url>
  </channel>
  <channel id="SPORT.TV2">
    <display-name lang="pt">SPORT.TV2</display-name>
    <url>http://www.meo.pt</url>
  </channel>
  <channel id="SPORT.TV3">
    <display-name lang="pt">SPORT.TV3</display-name>
    <url>http://www.meo.pt</url>
  </channel>
  <channel id="SPORT.TV4">
    <display-name lang="pt">SPORT.TV4</display-name>
    <url>http://www.meo.pt</url>
  </channel>
  <channel id="SPORT.TV5">
    <display-name lang="pt">SPORT.TV5</display-name>
    <url>http://www.meo.pt</url>
  </channel>
  <channel id="SPORT.TV6">
    <display-name lang="pt">SPORT.TV6</display-name>
    <url>http://www.meo.pt</url>
  </channel>
  <channel id="SPORT TV +">
    <display-name lang="pt">SPORT TV +</display-name>
    <url>http://www.meo.pt</url>
  </channel>
  <channel id="BTV">
    <display-name lang="pt">BTV</display-name>
    <url>http://www.meo.pt</url>
  </channel>
  <channel id="SPORTING TV">
    <display-name lang="pt">SPORTING TV</display-name>
    <url>http://www.meo.pt</url>
  </channel>
  <channel id="A BOLA TV">
    <display-name lang="pt">A BOLA TV</display-name>
    <url>http://www.meo.pt</url>
  </channel>
  <channel id="Canal 11">
    <display-name lang="pt">Canal 11</display-name>
    <url>http://www.meo.pt</url>
  </channel>
  <channel id="EUROSPORT 1">
    <display-name lang="pt">EUROSPORT 1</display-name>
    <url>http://www.meo.pt</url>
  </channel>
  <channel id="EUROSPORT 2">
    <display-name lang="pt">EUROSPORT 2</display-name>
    <url>http://www.meo.pt</url>
  </channel>
  <programme start="20231108000000 +0000" stop="20231108005000 +0000" channel="RECORD TV HD">
    <title lang="pt">Palavra Amiga - Bispo Macedo</title>
  </programme>
  <programme start="20231108005000 +0000" stop="20231108011500 +0000" channel="RECORD TV HD">
    <title lang="pt">Os Milagres De Jesus</title>
  </programme>
  <programme start="20231108011500 +0000" stop="20231108014500 +0000" channel="RECORD TV HD">
    <title lang="pt">Saindo Da Depressão</title>
  </programme>
  <programme start="20231108014500 +0000" stop="20231108021500 +0000" channel="RECORD TV HD">
    <title lang="pt">Prosperidade Com Deus</title>
  </programme>
  <programme start="20231108021500 +0000" stop="20231108024500 +0000" channel="RECORD TV HD">
    <title lang="pt">Terapia Do Amor</title>
  </programme>
  <programme start="20231108024500 +0000" stop="20231108030500 +0000" channel="RECORD TV HD">
    <title lang="pt">Programa Vencendo Os Vícios</title>
  </programme>
  <programme start="20231108030500 +0000" stop="20231108032500 +0000" channel="RECORD TV HD">
    <title lang="pt">Programa Luxemburgo</title>
  </programme>
  <programme start="20231108032500 +0000" stop="20231108033500 +0000" channel="RECORD TV HD">
    <title lang="pt">Ponto De Luz - Lisboa</title>
  </programme>
  <programme start="20231108033500 +0000" stop="20231108035500 +0000" channel="RECORD TV HD">
    <title lang="pt">Programa Alemanha</title>
  </programme>
  <programme start="20231108035500 +0000" stop="20231108042000 +0000" channel="RECORD TV HD">
    <title lang="pt">Programa França</title>
  </programme>
  <programme start="20231108042000 +0000" stop="20231108043000 +0000" channel="RECORD TV HD">
    <title lang="pt">Ponto De Luz - Porto</title>
  </programme>
  <programme start="20231108043000 +0000" stop="20231108045000 +0000" channel="RECORD TV HD">
    <title lang="pt">A Hora Do Milagre</title>
  </programme>
  <programme start="20231108045000 +0000" stop="20231108051000 +0000" channel="RECORD TV HD">
    <title lang="pt">Programa Itália</title>
  </programme>
  <programme start="20231108051000 +0000" stop="20231108052000 +0000" channel="RECORD TV HD">
    <title lang="pt">Ponto De Luz - Lisboa</title>
  </programme>
  <programme start="20231108052000 +0000" stop="20231108054000 +0000" channel="RECORD TV HD">
    <title lang="pt">Programa Madeira</title>
  </programme>
  <programme start="20231108054000 +0000" stop="20231108060000 +0000" channel="RECORD TV HD">
    <title lang="pt">Programa Suíça</title>
  </programme>
  <programme start="20231108060000 +0000" stop="20231108061500 +0000" channel="RECORD TV HD">
    <title lang="pt">Palavra Amiga - Bispo Macedo</title>
  </programme>
  <programme start="20231108061500 +0000" stop="20231108064000 +0000" channel="RECORD TV HD">
    <title lang="pt">Programa França</title>
  </programme>
  <programme start="20231108064000 +0000" stop="20231108070000 +0000" channel="RECORD TV HD">
    <title lang="pt">Programa Coimbra</title>
  </programme>
  <programme start="20231108070000 +0000" stop="20231108073000 +0000" channel="RECORD TV HD">
    <title lang="pt">Hora Do Milagre</title>
  </programme>
  <programme start="20231108073000 +0000" stop="20231108080000 +0000" channel="RECORD TV HD">
    <title lang="pt">Não Desista</title>
  </programme>
  <programme start="20231108080000 +0000" stop="20231108090000 +0000" channel="RECORD TV HD">
    <title lang="pt">Café Com Fé</title>
  </programme>
  <programme start="20231108090000 +0000" stop="20231108103000 +0000" channel="RECORD TV HD">
    <title lang="pt">Hoje Em Dia</title>
  </programme>
  <programme start="20231108103000 +0000" stop="20231108123000 +0000" channel="RECORD TV HD">
    <title lang="pt">Balanço Geral - SP</title>
  </programme>
  <programme start="20231108123000 +0000" stop="20231108140000 +0000" channel="RECORD TV HD">
    <title lang="pt">A Fazenda - Tudo A Ver</title>
  </programme>
  <programme start="20231108140000 +0000" stop="20231108140500 +0000" channel="RECORD TV HD">
    <title lang="pt">Portugal No Ar - Destaques</title>
  </programme>
  <programme start="20231108140500 +0000" stop="20231108150000 +0000" channel="RECORD TV HD">
    <title lang="pt">Bicho Do Mato</title>
  </programme>
  <programme start="20231108150000 +0000" stop="20231108153000 +0000" channel="RECORD TV HD">
    <title lang="pt">Os Milagres De Jesus</title>
  </programme>
  <programme start="20231108153000 +0000" stop="20231108163000 +0000" channel="RECORD TV HD">
    <title lang="pt">Reis</title>
  </programme>
  <programme start="20231108163000 +0000" stop="20231108173000 +0000" channel="RECORD TV HD">
    <title lang="pt">A Terra Prometida</title>
  </programme>
  <programme start="20231108173000 +0000" stop="20231108181500 +0000" channel="RECORD TV HD">
    <title lang="pt">Quando Me Apaixono</title>
  </programme>
  <programme start="20231108181500 +0000" stop="20231108191500 +0000" channel="RECORD TV HD">
    <title lang="pt">Bicho Do Mato</title>
  </programme>
  <programme start="20231108191500 +0000" stop="20231108200000 +0000" channel="RECORD TV HD">
    <title lang="pt">Fala Portugal</title>
  </programme>
  <programme start="20231108200000 +0000" stop="20231108210000 +0000" channel="RECORD TV HD">
    <title lang="pt">Reis</title>
  </programme>
  <programme start="20231108210000 +0000" stop="20231108220000 +0000" channel="RECORD TV HD">
    <title lang="pt">A Terra Prometida</title>
  </programme>
  <programme start="20231108220000 +0000" stop="20231109000000 +0000" channel="RECORD TV HD">
    <title lang="pt">Cidade Alerta - SP</title>
  </programme>
  <programme start="20231109000000 +0000" stop="20231109005000 +0000" channel="RECORD TV HD">
    <title lang="pt">Palavra Amiga - Bispo Macedo</title>
  </programme>
  <programme start="20231109005000 +0000" stop="20231109011500 +0000" channel="RECORD TV HD">
    <title lang="pt">Os Milagres De Jesus</title>
  </programme>
  <programme start="20231109011500 +0000" stop="20231109014500 +0000" channel="RECORD TV HD">
    <title lang="pt">Saindo Da Depressão</title>
  </programme>
  <programme start="20231109014500 +0000" stop="20231109021500 +0000" channel="RECORD TV HD">
    <title lang="pt">Prosperidade Com Deus</title>
  </programme>
  <programme start="20231109021500 +0000" stop="20231109024500 +0000" channel="RECORD TV HD">
    <title lang="pt">Terapia Do Amor</title>
  </programme>
  <programme start="20231109024500 +0000" stop="20231109025500 +0000" channel="RECORD TV HD">
    <title lang="pt">Ponto De Luz - Lisboa</title>
  </programme>
  <programme start="20231109025500 +0000" stop="20231109031500 +0000" channel="RECORD TV HD">
    <title lang="pt">Programa Vencendo Os Vícios</title>
  </programme>
  <programme start="20231109031500 +0000" stop="20231109033500 +0000" channel="RECORD TV HD">
    <title lang="pt">Programa Luxemburgo</title>
  </programme>
  <programme start="20231109033500 +0000" stop="20231109035500 +0000" channel="RECORD TV HD">
    <title lang="pt">Programa Alemanha</title>
  </programme>
  <programme start="20231109035500 +0000" stop="20231109042000 +0000" channel="RECORD TV HD">
    <title lang="pt">Programa França</title>
  </programme>
  <programme start="20231109042000 +0000" stop="20231109043000 +0000" channel="RECORD TV HD">
    <title lang="pt">Ponto De Luz - Porto</title>
  </programme>
  <programme start="20231109043000 +0000" stop="20231109045000 +0000" channel="RECORD TV HD">
    <title lang="pt">A Hora Do Milagre</title>
  </programme>
  <programme start="20231109045000 +0000" stop="20231109051000 +0000" channel="RECORD TV HD">
    <title lang="pt">Programa Itália</title>
  </programme>
  <programme start="20231109051000 +0000" stop="20231109052000 +0000" channel="RECORD TV HD">
    <title lang="pt">Ponto De Luz - Lisboa</title>
  </programme>
  <programme start="20231109052000 +0000" stop="20231109054000 +0000" channel="RECORD TV HD">
    <title lang="pt">Programa Madeira</title>
  </programme>
  <programme start="20231109054000 +0000" stop="20231109060000 +0000" channel="RECORD TV HD">
    <title lang="pt">Programa Suíça</title>
  </programme>
  <programme start="20231109060000 +0000" stop="20231109061500 +0000" channel="RECORD TV HD">
    <title lang="pt">Palavra Amiga - Bispo Macedo</title>
  </programme>
  <programme start="20231109061500 +0000" stop="20231109064000 +0000" channel="RECORD TV HD">
    <title lang="pt">Programa França</title>
  </programme>
  <programme start="20231109064000 +0000" stop="20231109070000 +0000" channel="RECORD TV HD">
    <title lang="pt">Programa Coimbra</title>
  </programme>
  <programme start="20231109070000 +0000" stop="20231109073000 +0000" channel="RECORD TV HD">
    <title lang="pt">Hora Do Milagre</title>
  </programme>
  <programme start="20231109073000 +0000" stop="20231109080000 +0000" channel="RECORD TV HD">
    <title lang="pt">Não Desista</title>
  </programme>
  <programme start="20231109080000 +0000" stop="20231109090000 +0000" channel="RECORD TV HD">
    <title lang="pt">Café Com Fé</title>
  </programme>
  <programme start="20231109090000 +0000" stop="20231109103000 +0000" channel="RECORD TV HD">
    <title lang="pt">Hoje Em Dia</title>
  </programme>
  <programme start="20231109103000 +0000" stop="20231109123000 +0000" channel="RECORD TV HD">
    <title lang="pt">Balanço Geral - SP</title>
  </programme>
  <programme start="20231109123000 +0000" stop="20231109140000 +0000" channel="RECORD TV HD">
    <title lang="pt">A Fazenda - Tudo A Ver</title>
  </programme>
  <programme start="20231109140000 +0000" stop="20231109140500 +0000" channel="RECORD TV HD">
    <title lang="pt">Portugal No Ar - Destaques</title>
  </programme>
  <programme start="20231109140500 +0000" stop="20231109150000 +0000" channel="RECORD TV HD">
    <title lang="pt">Bicho Do Mato</title>
  </programme>
  <programme start="20231109150000 +0000" stop="20231109153000 +0000" channel="RECORD TV HD">
    <title lang="pt">Os Milagres De Jesus</title>
  </programme>
  <programme start="20231109153000 +0000" stop="20231109163000 +0000" channel="RECORD TV HD">
    <title lang="pt">Reis</title>
  </programme>
  <programme start="20231109163000 +0000" stop="20231109173000 +0000" channel="RECORD TV HD">
    <title lang="pt">A Terra Prometida</title>
  </programme>
  <programme start="20231109173000 +0000" stop="20231109181500 +0000" channel="RECORD TV HD">
    <title lang="pt">Quando Me Apaixono</title>
  </programme>
  <programme start="20231109181500 +0000" stop="20231109191500 +0000" channel="RECORD TV HD">
    <title lang="pt">Bicho Do Mato</title>
  </programme>
  <programme start="20231109191500 +0000" stop="20231109200000 +0000" channel="RECORD TV HD">
    <title lang="pt">Fala Portugal</title>
  </programme>
  <programme start="20231109200000 +0000" stop="20231109210000 +0000" channel="RECORD TV HD">
    <title lang="pt">Reis</title>
  </programme>
  <programme start="20231109210000 +0000" stop="20231109220000 +0000" channel="RECORD TV HD">
    <title lang="pt">A Terra Prometida</title>
  </programme>
  <programme start="20231109220000 +0000" stop="20231110000000 +0000" channel="RECORD TV HD">
    <title lang="pt">Cidade Alerta - SP</title>
  </programme>
  <programme start="20231110000000 +0000" stop="20231110005000 +0000" channel="RECORD TV HD">
    <title lang="pt">Palavra Amiga - Bispo Macedo</title>
  </programme>
  <programme start="20231110005000 +0000" stop="20231110011500 +0000" channel="RECORD TV HD">
    <title lang="pt">Os Milagres De Jesus</title>
  </programme>
  <programme start="20231110011500 +0000" stop="20231110014500 +0000" channel="RECORD TV HD">
    <title lang="pt">Saindo Da Depressão</title>
  </programme>
  <programme start="20231110014500 +0000" stop="20231110021500 +0000" channel="RECORD TV HD">
    <title lang="pt">Prosperidade Com Deus</title>
  </programme>
  <programme start="20231110021500 +0000" stop="20231110024500 +0000" channel="RECORD TV HD">
    <title lang="pt">Terapia Do Amor</title>
  </programme>
  <programme start="20231110024500 +0000" stop="20231110025500 +0000" channel="RECORD TV HD">
    <title lang="pt">Ponto De Luz - Lisboa</title>
  </programme>
  <programme start="20231110025500 +0000" stop="20231110031500 +0000" channel="RECORD TV HD">
    <title lang="pt">Programa Vencendo Os Vícios</title>
  </programme>
  <programme start="20231110031500 +0000" stop="20231110033500 +0000" channel="RECORD TV HD">
    <title lang="pt">Programa Luxemburgo</title>
  </programme>
  <programme start="20231110033500 +0000" stop="20231110035500 +0000" channel="RECORD TV HD">
    <title lang="pt">Programa Alemanha</title>
  </programme>
  <programme start="20231110035500 +0000" stop="20231110042000 +0000" channel="RECORD TV HD">
    <title lang="pt">Programa França</title>
  </programme>
  <programme start="20231110042000 +0000" stop="20231110043000 +0000" channel="RECORD TV HD">
    <title lang="pt">Ponto De Luz - Porto</title>
  </programme>
  <programme start="20231110043000 +0000" stop="20231110045000 +0000" channel="RECORD TV HD">
    <title lang="pt">A Hora Do Milagre</title>
  </programme>
  <programme start="20231110045000 +0000" stop="20231110051000 +0000" channel="RECORD TV HD">
    <title lang="pt">Programa Itália</title>
  </programme>
  <programme start="20231110051000 +0000" stop="20231110052000 +0000" channel="RECORD TV HD">
    <title lang="pt">Ponto De Luz - Lisboa</title>
  </programme>
  <programme start="20231110052000 +0000" stop="20231110054000 +0000" channel="RECORD TV HD">
    <title lang="pt">Programa Madeira</title>
  </programme>
  <programme start="20231110054000 +0000" stop="20231110060000 +0000" channel="RECORD TV HD">
    <title lang="pt">Programa Suíça</title>
  </programme>
  <programme start="20231110060000 +0000" stop="20231110061500 +0000" channel="RECORD TV HD">
    <title lang="pt">Palavra Amiga - Bispo Macedo</title>
  </programme>
  <programme start="20231110061500 +0000" stop="20231110064000 +0000" channel="RECORD TV HD">
    <title lang="pt">Programa França</title>
  </programme>
  <programme start="20231110064000 +0000" stop="20231110070000 +0000" channel="RECORD TV HD">
    <title lang="pt">Programa Coimbra</title>
  </programme>
  <programme start="20231110070000 +0000" stop="20231110073000 +0000" channel="RECORD TV HD">
    <title lang="pt">Hora Do Milagre</title>
  </programme>
  <programme start="20231110073000 +0000" stop="20231110080000 +0000" channel="RECORD TV HD">
    <title lang="pt">Não Desista</title>
  </programme>
  <programme start="20231110080000 +0000" stop="20231110090000 +0000" channel="RECORD TV HD">
    <title lang="pt">Café Com Fé</title>
  </programme>
  <programme start="20231110090000 +0000" stop="20231110103000 +0000" channel="RECORD TV HD">
    <title lang="pt">Hoje Em Dia</title>
  </programme>
  <programme start="20231110103000 +0000" stop="20231110123000 +0000" channel="RECORD TV HD">
    <title lang="pt">Balanço Geral - SP</title>
  </programme>
  <programme start="20231110123000 +0000" stop="20231110140000 +0000" channel="RECORD TV HD">
    <title lang="pt">A Fazenda - Tudo A Ver</title>
  </programme>
  <programme start="20231110140000 +0000" stop="20231110140500 +0000" channel="RECORD TV HD">
    <title lang="pt">Portugal No Ar - Destaques</title>
  </programme>
  <programme start="20231110140500 +0000" stop="20231110150000 +0000" channel="RECORD TV HD">
    <title lang="pt">Bicho Do Mato</title>
  </programme>
  <programme start="20231110150000 +0000" stop="20231110153000 +0000" channel="RECORD TV HD">
    <title lang="pt">Os Milagres De Jesus</title>
  </programme>
  <programme start="20231110153000 +0000" stop="20231110163000 +0000" channel="RECORD TV HD">
    <title lang="pt">Reis</title>
  </programme>
  <programme start="20231110163000 +0000" stop="20231110173000 +0000" channel="RECORD TV HD">
    <title lang="pt">A Terra Prometida</title>
  </programme>
  <programme start="20231110173000 +0000" stop="20231110181500 +0000" channel="RECORD TV HD">
    <title lang="pt">Quando Me Apaixono</title>
  </programme>
  <programme start="20231110181500 +0000" stop="20231110191500 +0000" channel="RECORD TV HD">
    <title lang="pt">Bicho Do Mato</title>
  </programme>
  <programme start="20231110191500 +0000" stop="20231110200000 +0000" channel="RECORD TV HD">
    <title lang="pt">Fala Portugal</title>
  </programme>
  <programme start="20231110200000 +0000" stop="20231110210000 +0000" channel="RECORD TV HD">
    <title lang="pt">Reis</title>
  </programme>
  <programme start="20231110210000 +0000" stop="20231110220000 +0000" channel="RECORD TV HD">
    <title lang="pt">A Terra Prometida</title>
  </programme>
  <programme start="20231110220000 +0000" stop="20231111000000 +0000" channel="RECORD TV HD">
    <title lang="pt">Cidade Alerta - SP</title>
  </programme>
  <programme start="20231111000000 +0000" stop="20231111005000 +0000" channel="RECORD TV HD">
    <title lang="pt">Palavra Amiga - Bispo Macedo</title>
  </programme>
  <programme start="20231111005000 +0000" stop="20231111011500 +0000" channel="RECORD TV HD">
    <title lang="pt">Os Milagres De Jesus</title>
  </programme>
  <programme start="20231111011500 +0000" stop="20231111014500 +0000" channel="RECORD TV HD">
    <title lang="pt">Hora Do Milagre</title>
  </programme>
  <programme start="20231111014500 +0000" stop="20231111021500 +0000" channel="RECORD TV HD">
    <title lang="pt">Prosperidade Com Deus</title>
  </programme>
  <programme start="20231111021500 +0000" stop="20231111024500 +0000" channel="RECORD TV HD">
    <title lang="pt">Terapia Do Amor</title>
  </programme>
  <programme start="20231111024500 +0000" stop="20231111030500 +0000" channel="RECORD TV HD">
    <title lang="pt">Programa Vencendo Os Vícios</title>
  </programme>
  <programme start="20231111030500 +0000" stop="20231111032500 +0000" channel="RECORD TV HD">
    <title lang="pt">Programa Luxemburgo</title>
  </programme>
  <programme start="20231111032500 +0000" stop="20231111034000 +0000" channel="RECORD TV HD">
    <title lang="pt">Programa Alemanha</title>
  </programme>
  <programme start="20231111034000 +0000" stop="20231111040000 +0000" channel="RECORD TV HD">
    <title lang="pt">Programa Coimbra</title>
  </programme>
  <programme start="20231111040000 +0000" stop="20231111041000 +0000" channel="RECORD TV HD">
    <title lang="pt">Ponto De Luz - Lisboa</title>
  </programme>
  <programme start="20231111041000 +0000" stop="20231111043000 +0000" channel="RECORD TV HD">
    <title lang="pt">Programa Itália</title>
  </programme>
  <programme start="20231111043000 +0000" stop="20231111045000 +0000" channel="RECORD TV HD">
    <title lang="pt">Programa Madeira</title>
  </programme>
  <programme start="20231111045000 +0000" stop="20231111051000 +0000" channel="RECORD TV HD">
    <title lang="pt">Programa Suíça</title>
  </programme>
  <programme start="20231111051000 +0000" stop="20231111052000 +0000" channel="RECORD TV HD">
    <title lang="pt">Ponto De Luz - Lisboa</title>
  </programme>
  <programme start="20231111052000 +0000" stop="20231111054500 +0000" channel="RECORD TV HD">
    <title lang="pt">Programa França</title>
  </programme>
  <programme start="20231111054500 +0000" stop="20231111060000 +0000" channel="RECORD TV HD">
    <title lang="pt">Palavra Amiga - Bispo Macedo</title>
  </programme>
  <programme start="20231111060000 +0000" stop="20231111063000 +0000" channel="RECORD TV HD">
    <title lang="pt">Prosperidade Com Deus</title>
  </programme>
  <programme start="20231111063000 +0000" stop="20231111070000 +0000" channel="RECORD TV HD">
    <title lang="pt">Hora Do Milagre</title>
  </programme>
  <programme start="20231111070000 +0000" stop="20231111073000 +0000" channel="RECORD TV HD">
    <title lang="pt">Não Desista</title>
  </programme>
  <programme start="20231111073000 +0000" stop="20231111080000 +0000" channel="RECORD TV HD">
    <title lang="pt">Problemas E Soluções</title>
  </programme>
  <programme start="20231111080000 +0000" stop="20231111090000 +0000" channel="RECORD TV HD">
    <title lang="pt">Record Kids</title>
  </programme>
  <programme start="20231111090000 +0000" stop="20231111104500 +0000" channel="RECORD TV HD">
    <title lang="pt">Hoje Em Dia</title>
  </programme>
  <programme start="20231111104500 +0000" stop="20231111113000 +0000" channel="RECORD TV HD">
    <title lang="pt">Soltando Os Bichos</title>
  </programme>
  <programme start="20231111113000 +0000" stop="20231111123000 +0000" channel="RECORD TV HD">
    <title lang="pt">The Love School</title>
  </programme>
  <programme start="20231111123000 +0000" stop="20231111130000 +0000" channel="RECORD TV HD">
    <title lang="pt">A Fazenda - Tudo A Ver</title>
  </programme>
  <programme start="20231111130000 +0000" stop="20231111153000 +0000" channel="RECORD TV HD">
    <title lang="pt">Quando Me Apaixono - Compacto</title>
  </programme>
  <programme start="20231111153000 +0000" stop="20231111164500 +0000" channel="RECORD TV HD">
    <title lang="pt">Câmera Record</title>
  </programme>
  <programme start="20231111164500 +0000" stop="20231111193000 +0000" channel="RECORD TV HD">
    <title lang="pt">Vai Dar Namoro &amp; Dança Gatinho</title>
  </programme>
  <programme start="20231111193000 +0000" stop="20231111200000 +0000" channel="RECORD TV HD">
    <title lang="pt">Giro</title>
  </programme>
  <programme start="20231111200000 +0000" stop="20231112000000 +0000" channel="RECORD TV HD">
    <title lang="pt">A Terra Prometida - Compacto</title>
  </programme>
  <programme start="20231112000000 +0000" stop="20231112005000 +0000" channel="RECORD TV HD">
    <title lang="pt">Palavra Amiga - Bispo Macedo</title>
  </programme>
  <programme start="20231112005000 +0000" stop="20231112015500 +0000" channel="RECORD TV HD">
    <title lang="pt">Entrelinhas</title>
  </programme>
  <programme start="20231112015500 +0000" stop="20231112022500 +0000" channel="RECORD TV HD">
    <title lang="pt">Prosperidade Com Deus</title>
  </programme>
  <programme start="20231112022500 +0000" stop="20231112025500 +0000" channel="RECORD TV HD">
    <title lang="pt">Terapia Do Amor</title>
  </programme>
  <programme start="20231112025500 +0000" stop="20231112031500 +0000" channel="RECORD TV HD">
    <title lang="pt">Programa Vencendo Os Vícios</title>
  </programme>
  <programme start="20231112031500 +0000" stop="20231112033000 +0000" channel="RECORD TV HD">
    <title lang="pt">Programa Alemanha</title>
  </programme>
  <programme start="20231112033000 +0000" stop="20231112035500 +0000" channel="RECORD TV HD">
    <title lang="pt">Programa França</title>
  </programme>
  <programme start="20231112035500 +0000" stop="20231112041500 +0000" channel="RECORD TV HD">
    <title lang="pt">Programa Itália</title>
  </programme>
  <programme start="20231112041500 +0000" stop="20231112043500 +0000" channel="RECORD TV HD">
    <title lang="pt">Programa Madeira</title>
  </programme>
  <programme start="20231112043500 +0000" stop="20231112045500 +0000" channel="RECORD TV HD">
    <title lang="pt">Programa Vencendo Os Vícios</title>
  </programme>
  <programme start="20231112045500 +0000" stop="20231112051500 +0000" channel="RECORD TV HD">
    <title lang="pt">Programa Suíça</title>
  </programme>
  <programme start="20231112051500 +0000" stop="20231112053500 +0000" channel="RECORD TV HD">
    <title lang="pt">Programa Coimbra</title>
  </programme>
  <programme start="20231112053500 +0000" stop="20231112054500 +0000" channel="RECORD TV HD">
    <title lang="pt">Ponto De Luz - Lisboa</title>
  </programme>
  <programme start="20231112054500 +0000" stop="20231112060000 +0000" channel="RECORD TV HD">
    <title lang="pt">Palavra Amiga - Bispo Macedo</title>
  </programme>
  <programme start="20231112060000 +0000" stop="20231112063000 +0000" channel="RECORD TV HD">
    <title lang="pt">Prosperidade Com Deus</title>
  </programme>
  <programme start="20231112063000 +0000" stop="20231112070000 +0000" channel="RECORD TV HD">
    <title lang="pt">Hora Do Milagre</title>
  </programme>
  <programme start="20231112070000 +0000" stop="20231112073000 +0000" channel="RECORD TV HD">
    <title lang="pt">Não Desista</title>
  </programme>
  <programme start="20231112073000 +0000" stop="20231112080000 +0000" channel="RECORD TV HD">
    <title lang="pt">Problemas E Soluções</title>
  </programme>
  <programme start="20231112080000 +0000" stop="20231112090000 +0000" channel="RECORD TV HD">
    <title lang="pt">Santo Culto - Bispo Macedo</title>
  </programme>
  <programme start="20231112090000 +0000" stop="20231112111500 +0000" channel="RECORD TV HD">
    <title lang="pt">Record Kids</title>
  </programme>
  <programme start="20231112111500 +0000" stop="20231112143000 +0000" channel="RECORD TV HD">
    <title lang="pt">Domingo Espetacular</title>
  </programme>
  <programme start="20231112143000 +0000" stop="20231112144500 +0000" channel="RECORD TV HD">
    <title lang="pt">Insólito</title>
  </programme>
  <programme start="20231112144500 +0000" stop="20231112170000 +0000" channel="RECORD TV HD">
    <title lang="pt">Reis - Compacto</title>
  </programme>
  <programme start="20231112170000 +0000" stop="20231112173000 +0000" channel="RECORD TV HD">
    <title lang="pt">Palco</title>
  </programme>
  <programme start="20231112173000 +0000" stop="20231112220000 +0000" channel="RECORD TV HD">
    <title lang="pt">Hora Do Faro</title>
  </programme>
  <programme start="20231112220000 +0000" stop="20231113010000 +0000" channel="RECORD TV HD">
    <title lang="pt">Entrelinhas</title>
  </programme>
  <programme start="20231113010000 +0000" stop="20231113043000 +0000" channel="RECORD TV HD">
    <title lang="pt">Domingo Espetacular</title>
  </programme>
  <programme start="20231113043000 +0000" stop="20231113050000 +0000" channel="RECORD TV HD">
    <title lang="pt">Prosperidade Com Deus</title>
  </programme>
  <programme start="20231113050000 +0000" stop="20231113052000 +0000" channel="RECORD TV HD">
    <title lang="pt">Programa Madeira</title>
  </programme>
  <programme start="20231113052000 +0000" stop="20231113054000 +0000" channel="RECORD TV HD">
    <title lang="pt">Programa Vencendo Os Vícios</title>
  </programme>
  <programme start="20231113054000 +0000" stop="20231113060000 +0000" channel="RECORD TV HD">
    <title lang="pt">A Hora Do Milagre</title>
  </programme>
  <programme start="20231113060000 +0000" stop="20231113061500 +0000" channel="RECORD TV HD">
    <title lang="pt">Palavra Amiga - Bispo Macedo</title>
  </programme>
  <programme start="20231113061500 +0000" stop="20231113064000 +0000" channel="RECORD TV HD">
    <title lang="pt">Programa França</title>
  </programme>
  <programme start="20231113064000 +0000" stop="20231113065000 +0000" channel="RECORD TV HD">
    <title lang="pt">Ponto De Luz - Lisboa</title>
  </programme>
  <programme start="20231113065000 +0000" stop="20231113071000 +0000" channel="RECORD TV HD">
    <title lang="pt">Programa Coimbra</title>
  </programme>
  <programme start="20231113071000 +0000" stop="20231113073000 +0000" channel="RECORD TV HD">
    <title lang="pt">Programa Vencendo Os Vícios</title>
  </programme>
  <programme start="20231113073000 +0000" stop="20231113080000 +0000" channel="RECORD TV HD">
    <title lang="pt">Hora Do Milagre</title>
  </programme>
  <programme start="20231113080000 +0000" stop="20231113090000 +0000" channel="RECORD TV HD">
    <title lang="pt">Café Com Fé</title>
  </programme>
  <programme start="20231113090000 +0000" stop="20231113123000 +0000" channel="RECORD TV HD">
    <title lang="pt">Domingo Espetacular</title>
  </programme>
  <programme start="20231113123000 +0000" stop="20231113140000 +0000" channel="RECORD TV HD">
    <title lang="pt">A Fazenda - Tudo A Ver</title>
  </programme>
  <programme start="20231113140000 +0000" stop="20231113140500 +0000" channel="RECORD TV HD">
    <title lang="pt">Portugal No Ar - Destaques</title>
  </programme>
  <programme start="20231113140500 +0000" stop="20231113150000 +0000" channel="RECORD TV HD">
    <title lang="pt">Bicho Do Mato</title>
  </programme>
  <programme start="20231113150000 +0000" stop="20231113153000 +0000" channel="RECORD TV HD">
    <title lang="pt">Os Milagres De Jesus</title>
  </programme>
  <programme start="20231113153000 +0000" stop="20231113163000 +0000" channel="RECORD TV HD">
    <title lang="pt">Reis</title>
  </programme>
  <programme start="20231113163000 +0000" stop="20231113173000 +0000" channel="RECORD TV HD">
    <title lang="pt">A Terra Prometida</title>
  </programme>
  <programme start="20231113173000 +0000" stop="20231113181500 +0000" channel="RECORD TV HD">
    <title lang="pt">Quando Me Apaixono</title>
  </programme>
  <programme start="20231113181500 +0000" stop="20231113191500 +0000" channel="RECORD TV HD">
    <title lang="pt">Bicho Do Mato</title>
  </programme>
  <programme start="20231113191500 +0000" stop="20231113200000 +0000" channel="RECORD TV HD">
    <title lang="pt">Fala Portugal</title>
  </programme>
  <programme start="20231113200000 +0000" stop="20231113210000 +0000" channel="RECORD TV HD">
    <title lang="pt">Reis</title>
  </programme>
  <programme start="20231113210000 +0000" stop="20231113220000 +0000" channel="RECORD TV HD">
    <title lang="pt">A Terra Prometida</title>
  </programme>
  <programme start="20231113220000 +0000" stop="20231113230000 +0000" channel="RECORD TV HD">
    <title lang="pt">Alerta Portugal</title>
  </programme>
  <programme start="20231113230000 +0000" stop="20231114000000 +0000" channel="RECORD TV HD">
    <title lang="pt">Cidade Alerta - SP</title>
  </programme>
  <programme start="20231114000000 +0000" stop="20231114005000 +0000" channel="RECORD TV HD">
    <title lang="pt">Palavra Amiga - Bispo Macedo</title>
  </programme>
  <programme start="20231114005000 +0000" stop="20231114011500 +0000" channel="RECORD TV HD">
    <title lang="pt">Os Milagres De Jesus</title>
  </programme>
  <programme start="20231114011500 +0000" stop="20231114014500 +0000" channel="RECORD TV HD">
    <title lang="pt">Saindo Da Depressão</title>
  </programme>
  <programme start="20231114014500 +0000" stop="20231114015500 +0000" channel="RECORD TV HD">
    <title lang="pt">Ponto De Luz - Lisboa</title>
  </programme>
  <programme start="20231114015500 +0000" stop="20231114022500 +0000" channel="RECORD TV HD">
    <title lang="pt">Prosperidade Com Deus</title>
  </programme>
  <programme start="20231114022500 +0000" stop="20231114025500 +0000" channel="RECORD TV HD">
    <title lang="pt">Terapia Do Amor</title>
  </programme>
  <programme start="20231114025500 +0000" stop="20231114031500 +0000" channel="RECORD TV HD">
    <title lang="pt">Programa Vencendo Os Vícios</title>
  </programme>
  <programme start="20231114031500 +0000" stop="20231114033500 +0000" channel="RECORD TV HD">
    <title lang="pt">Programa Luxemburgo</title>
  </programme>
  <programme start="20231114033500 +0000" stop="20231114034500 +0000" channel="RECORD TV HD">
    <title lang="pt">Ponto De Luz - Porto</title>
  </programme>
  <programme start="20231114034500 +0000" stop="20231114040500 +0000" channel="RECORD TV HD">
    <title lang="pt">Programa Alemanha</title>
  </programme>
  <programme start="20231114040500 +0000" stop="20231114043000 +0000" channel="RECORD TV HD">
    <title lang="pt">Programa França</title>
  </programme>
  <programme start="20231114043000 +0000" stop="20231114044000 +0000" channel="RECORD TV HD">
    <title lang="pt">Ponto De Luz - Lisboa</title>
  </programme>
  <programme start="20231114044000 +0000" stop="20231114050000 +0000" channel="RECORD TV HD">
    <title lang="pt">A Hora Do Milagre</title>
  </programme>
  <programme start="20231114050000 +0000" stop="20231114052000 +0000" channel="RECORD TV HD">
    <title lang="pt">Programa Itália</title>
  </programme>
  <programme start="20231114052000 +0000" stop="20231114054000 +0000" channel="RECORD TV HD">
    <title lang="pt">Programa Madeira</title>
  </programme>
  <programme start="20231114054000 +0000" stop="20231114060000 +0000" channel="RECORD TV HD">
    <title lang="pt">Programa Suíça</title>
  </programme>
  <programme start="20231114060000 +0000" stop="20231114061500 +0000" channel="RECORD TV HD">
    <title lang="pt">Palavra Amiga - Bispo Macedo</title>
  </programme>
  <programme start="20231114061500 +0000" stop="20231114064000 +0000" channel="RECORD TV HD">
    <title lang="pt">Programa França</title>
  </programme>
  <programme start="20231114064000 +0000" stop="20231114070000 +0000" channel="RECORD TV HD">
    <title lang="pt">Programa Coimbra</title>
  </programme>
  <programme start="20231114070000 +0000" stop="20231114073000 +0000" channel="RECORD TV HD">
    <title lang="pt">Hora Do Milagre</title>
  </programme>
  <programme start="20231114073000 +0000" stop="20231114080000 +0000" channel="RECORD TV HD">
    <title lang="pt">Não Desista</title>
  </programme>
  <programme start="20231114080000 +0000" stop="20231114090000 +0000" channel="RECORD TV HD">
    <title lang="pt">Café Com Fé</title>
  </programme>
  <programme start="20231114090000 +0000" stop="20231114103000 +0000" channel="RECORD TV HD">
    <title lang="pt">Hoje Em Dia</title>
  </programme>
  <programme start="20231114103000 +0000" stop="20231114123000 +0000" channel="RECORD TV HD">
    <title lang="pt">Balanço Geral - SP</title>
  </programme>
  <programme start="20231114123000 +0000" stop="20231114140000 +0000" channel="RECORD TV HD">
    <title lang="pt">A Fazenda - Tudo A Ver</title>
  </programme>
  <programme start="20231114140000 +0000" stop="20231114140500 +0000" channel="RECORD TV HD">
    <title lang="pt">Portugal No Ar - Destaques</title>
  </programme>
  <programme start="20231114140500 +0000" stop="20231114150000 +0000" channel="RECORD TV HD">
    <title lang="pt">Bicho Do Mato</title>
  </programme>
  <programme start="20231114150000 +0000" stop="20231114153000 +0000" channel="RECORD TV HD">
    <title lang="pt">Os Milagres De Jesus</title>
  </programme>
  <programme start="20231114153000 +0000" stop="20231114163000 +0000" channel="RECORD TV HD">
    <title lang="pt">Reis</title>
  </programme>
  <programme start="20231114163000 +0000" stop="20231114173000 +0000" channel="RECORD TV HD">
    <title lang="pt">A Terra Prometida</title>
  </programme>
  <programme start="20231114173000 +0000" stop="20231114181500 +0000" channel="RECORD TV HD">
    <title lang="pt">Quando Me Apaixono</title>
  </programme>
  <programme start="20231114181500 +0000" stop="20231114191500 +0000" channel="RECORD TV HD">
    <title lang="pt">Bicho Do Mato</title>
  </programme>
  <programme start="20231114191500 +0000" stop="20231114200000 +0000" channel="RECORD TV HD">
    <title lang="pt">Fala Portugal</title>
  </programme>
  <programme start="20231114200000 +0000" stop="20231114210000 +0000" channel="RECORD TV HD">
    <title lang="pt">Reis</title>
  </programme>
  <programme start="20231114210000 +0000" stop="20231114220000 +0000" channel="RECORD TV HD">
    <title lang="pt">A Terra Prometida</title>
  </programme>
  <programme start="20231114220000 +0000" stop="20231115000000 +0000" channel="RECORD TV HD">
    <title lang="pt">Cidade Alerta - SP</title>
  </programme>
</tv>